logging_bullet_train/VERSION
logging_bullet_train/__init__.py
logging_bullet_train/version.py
logging_bullet_train-0.2.0.dist-info/LICENSE
logging_bullet_train-0.2.0.dist-info/METADATA
logging_bullet_train-0.2.0.dist-info/WHEEL
logging_bullet_train-0.2.0.dist-info/RECORD
